layra/__init__.py
layra/cli.py
layra/core/__init__.py
layra/core/config.py
layra/core/exceptions.py
layra/core/generator.py
layra/core/git.py
layra/core/repository.py
layra/core/storage.py
layra/core/templates.py
layra/core/variables.py
layra/models/__init__.py
layra/models/component.py
layra/models/profile.py
layra/models/source.py
layra/templates/base/.gitignore
layra/templates/base/README.md
layra-0.0.1.dist-info/METADATA
layra-0.0.1.dist-info/WHEEL
layra-0.0.1.dist-info/entry_points.txt
layra-0.0.1.dist-info/licenses/LICENSE
layra-0.0.1.dist-info/RECORD
