Metadata-Version: 2.4
Name: layra
Version: 0.0.1
Summary: Python project boilerplate generator with modern tooling and intelligent CLI for rapid scaffolding
Project-URL: Repository, https://github.com/flacy/layra
Author-email: Andrew Krylov <any@lunte.dev>
License-Expression: MIT
License-File: LICENSE
Classifier: Development Status :: 3 - Alpha
Classifier: Intended Audience :: Developers
Classifier: License :: OSI Approved :: MIT License
Classifier: Programming Language :: Python :: 3
Classifier: Programming Language :: Python :: 3.9
Classifier: Programming Language :: Python :: 3.10
Classifier: Programming Language :: Python :: 3.11
Classifier: Programming Language :: Python :: 3.12
Classifier: Programming Language :: Python :: 3.13
Requires-Python: >=3.9
Requires-Dist: pyyaml>=6.0.2
Requires-Dist: tomli-w>=0.4.0
Requires-Dist: typer>=0.15.4
